{
  "gitSyncId": "683e21591b989748a426a418_3c399587-6931-435d-a07e-4e29ce891854",
  "id": "Gestion sous recette_Delete_composants_sous_recette",
  "pluginId": "postgres-plugin",
  "pluginType": "DB",
  "unpublishedAction": {
    "actionConfiguration": {
      "body": "DELETE FROM newroseclaire.composants_sous_recettes WHERE id_sous_recette = '{{ Table1.triggeredRow.id_sous_recette }}';",
      "encodeParamsToggle": true,
      "paginationType": "NONE",
      "pluginSpecifiedTemplates": [
        {
          "value": true
        }
      ],
      "timeoutInMillisecond": 10000
    },
    "confirmBeforeExecute": false,
    "datasource": {
      "id": "roseclaire database",
      "isAutoGenerated": false,
      "name": "roseclaire database",
      "pluginId": "postgres-plugin"
    },
    "dynamicBindingPathList": [
      {
        "key": "body"
      }
    ],
    "name": "Delete_composants_sous_recette",
    "pageId": "Gestion sous recette",
    "runBehaviour": "MANUAL",
    "userSetOnLoad": false
  }
}