{
  "gitSyncId": "683e21591b989748a426a418_ad121b46-1d4b-43a5-af44-d9cefbd8b57c",
  "id": "Edit_SR_UpdateSousRecette",
  "pluginId": "postgres-plugin",
  "pluginType": "DB",
  "unpublishedAction": {
    "actionConfiguration": {
      "body": "UPDATE newroseclaire.sous_recettes\nSET\n  nom = {{ this.params.nom }},\n  description = {{ this.params.description }},\n  quantite_produite = {{ this.params.quantite_produit }},\n  id_unite = {{ this.params.id_unite }}\nWHERE id_sous_recette = {{ appsmith.URL.queryParams.SRId }};\n",
      "encodeParamsToggle": true,
      "paginationType": "NONE",
      "pluginSpecifiedTemplates": [
        {
          "value": true
        }
      ],
      "timeoutInMillisecond": 10000
    },
    "confirmBeforeExecute": false,
    "datasource": {
      "id": "roseclaire database",
      "isAutoGenerated": false,
      "name": "roseclaire database",
      "pluginId": "postgres-plugin"
    },
    "dynamicBindingPathList": [
      {
        "key": "body"
      }
    ],
    "name": "UpdateSousRecette",
    "pageId": "Edit_SR",
    "runBehaviour": "MANUAL",
    "userSetOnLoad": false
  }
}