{
  "gitSyncId": "683e21591b989748a426a418_e18f5be8-7bd7-412a-bff1-79de8048fce9",
  "id": "Edit_RF_JSObject1.enrichData",
  "pluginId": "js-plugin",
  "pluginType": "JS",
  "unpublishedAction": {
    "actionConfiguration": {
      "encodeParamsToggle": true,
      "jsArguments": [
        {
          "name": "raw"
        }
      ],
      "paginationType": "NONE",
      "timeoutInMillisecond": 10000
    },
    "collectionId": "Edit_RF_JSObject1",
    "confirmBeforeExecute": false,
    "datasource": {
      "isAutoGenerated": false,
      "name": "UNUSED_DATASOURCE",
      "pluginId": "js-plugin"
    },
    "dynamicBindingPathList": [
      {
        "key": "body"
      }
    ],
    "fullyQualifiedName": "JSObject1.enrichData",
    "name": "enrichData",
    "pageId": "Edit_RF",
    "runBehaviour": "MANUAL",
    "userSetOnLoad": false
  }
}